<?xml version='1.0' encoding='UTF-8'?>
<song xmlns="http://openlyrics.info/namespace/2009/song" version="0.8" createdIn="OpenLP 2.4.5" modifiedIn="OpenLP 2.4.5" modifiedDate="2017-04-15T20:05:32">
  <properties>
    <titles>
      <title>MP1250 Your mercy taught us</title>
    </titles>
    <verseOrder>v1 v2 c1</verseOrder>
    <authors>
      <author>Author Unknown</author>
    </authors>
  </properties>
  <lyrics>
    <verse name="v1">
      <lines><br/>Your mercy taught us how to dance<br/>To celebrate with all we have<br/>And we'll dance to thank You for mercy</lines>
    </verse>
    <verse name="v2">
      <lines><br/>Your glory taught us how to shout<br/>We'll lift Your name in all the earth<br/>And we'll shout to the praise of Your glory</lines>
    </verse>
    <verse name="c1">
      <lines><br/>And we'll be a dancing generation<br/>Dancing because of Your great mercy Lord<br/>Your great mercy, Lord<br/>And we'll be a shouting generation<br/>Shouting because of Your great glory Lord<br/>Your great glory, Lord</lines>
    </verse>
  </lyrics>
</song>
