<?xml version='1.0' encoding='UTF-8'?>
<song xmlns="http://openlyrics.info/namespace/2009/song" version="0.8" createdIn="OpenLP 2.4.5" modifiedIn="OpenLP 2.4.5" modifiedDate="2017-04-15T20:04:10">
  <properties>
    <titles>
      <title>MP536 On a hill far away</title>
    </titles>
    <verseOrder>v1 c1 v2 c1 v3 c1 v4 c1</verseOrder>
    <authors>
      <author>Author Unknown</author>
    </authors>
  </properties>
  <lyrics>
    <verse name="v1">
      <lines><br/>On a hill far away,<br/>Stood an old rugged cross,<br/>The emblem of suffering and shame;<br/>And I loved that old cross<br/>Where the dearest and best<br/>For a world of lost sinners was slain.</lines>
    </verse>
    <verse name="v2">
      <lines><br/>O, that old rugged cross,<br/>So despised by the world,<br/>Has a wondrous attraction for me:<br/>For the dear Lamb of God<br/>Left His glory above<br/>To bear it to dark Calvary.</lines>
    </verse>
    <verse name="v3">
      <lines><br/>In the old rugged cross,<br/>Stained with blood so divine,<br/>A wondrous beauty I see.<br/>For 'twas on that old cross<br/>Jesus suffered and died<br/>To pardon and sanctify me.</lines>
    </verse>
    <verse name="v4">
      <lines><br/>To the old rugged cross<br/>I will ever be true,<br/>Its shame and reproach gladly bear.<br/>Then he'll call me some day<br/>To my home far away;<br/>There His glory for ever I'll share.</lines>
    </verse>
    <verse name="c1">
      <lines><br/>So I'll cherish the old rugged cross,<br/>Till my trophies at last I lay down;<br/>I will cling to the old rugged cross<br/>And exchange it some day for a crown.</lines>
    </verse>
  </lyrics>
</song>
