<?xml version='1.0' encoding='UTF-8'?>
<song xmlns="http://openlyrics.info/namespace/2009/song" version="0.8" createdIn="OpenLP 2.4.5" modifiedIn="OpenLP 2.4.5" modifiedDate="2017-04-15T20:04:14">
  <properties>
    <titles>
      <title>MP571 Reigning In All Splendour</title>
    </titles>
    <verseOrder>v1</verseOrder>
    <authors>
      <author>Author Unknown</author>
    </authors>
  </properties>
  <lyrics>
    <verse name="v1">
      <lines><br/>Reigning in all splendour,<br/>Victorious love,<br/>Christ Jesus the Saviour,<br/>Transcendent above.<br/>All earthly dominions<br/>And kingdoms shall fall,<br/>For His name is Jesus<br/>And He is the Lord.<br/>He is Lord,<br/>He is Lord,<br/>He is Lord,<br/>He is Lord.</lines>
    </verse>
  </lyrics>
</song>
