<?xml version='1.0' encoding='UTF-8'?>
<song xmlns="http://openlyrics.info/namespace/2009/song" version="0.8" createdIn="OpenLP 2.4.5" modifiedIn="OpenLP 2.4.5" modifiedDate="2018-05-17T20:37:01">
  <properties>
    <titles>
      <title>MP821,SF377 Down The Mountain The River Flows</title>
    </titles>
    <verseOrder>v1 c1 v2 c1 v3 c1</verseOrder>
    <authors>
      <author>Author Unknown</author>
    </authors>
  </properties>
  <lyrics>
    <verse name="v1">
      <lines><br/>Down the mountain the river flows,<br/>And it brings refreshing wherever it goes.<br/>Through the valleys and over the fields,<br/>The river is rushing and the river is here.</lines>
    </verse>
    <verse name="v2">
      <lines><br/>The river of God is teeming with life,<br/>And all who touch it can be revived.<br/>And those who linger on this river's shore<br/>Will come back thirsting for more of the Lord.</lines>
    </verse>
    <verse name="v3">
      <lines><br/>Up to the mountain we love to go<br/>To find the presence of the Lord.<br/>Along the banks of the river we run,<br/>We dance with laughter, giving praise to the Son.</lines>
    </verse>
    <verse name="c1">
      <lines><br/>The river of God sets our feet a-dancing,<br/>The river of God fills our heart with cheer;<br/>The river of God fills our mouths with laughter,<br/>And we rejoice for the river is here.</lines>
    </verse>
  </lyrics>
</song>
