<?xml version='1.0' encoding='UTF-8'?>
<song xmlns="http://openlyrics.info/namespace/2009/song" version="0.8" createdIn="OpenLP 2.4.6" modifiedIn="OpenLP 2.4.6" modifiedDate="2018-12-09T19:17:53">
  <properties>
    <titles>
      <title>SF171 Hark the glad sound! The Saviour comes,</title>
    </titles>
    <verseOrder>v1 v2 v3 v4</verseOrder>
    <authors>
      <author>Philip Doddridge (1702-1751)</author>
    </authors>
  </properties>
  <lyrics>
    <verse name="v1">
      <lines><br/>Hark the glad sound! The Saviour comes,<br/>the Saviour promised long;<br/>let every heart prepare a throne,<br/>and every voice a song.</lines>
    </verse>
    <verse name="v2">
      <lines><br/>He comes the prisoners to release,<br/>in Satan's bondage held;<br/>the gates of brass before him burst,<br/>the iron fetters yield.</lines>
    </verse>
    <verse name="v3">
      <lines><br/>He comes the broken heart to bind,<br/>the bleeding soul to cure,<br/>and with the treasures of his grace<br/>to enrich the humble poor.</lines>
    </verse>
    <verse name="v4">
      <lines><br/>Our glad hosannas, Prince of Peace,<br/>your welcome shall proclaim,<br/>and heaven's eternal arches ring<br/>with your beloved name.</lines>
    </verse>
  </lyrics>
</song>
