<?xml version='1.0' encoding='UTF-8'?>
<song xmlns="http://openlyrics.info/namespace/2009/song" version="0.8" createdIn="OpenLP 2.4.6" modifiedIn="OpenLP 2.4.6" modifiedDate="2018-11-12T16:36:22">
  <properties>
    <titles>
      <title>SF26 I rejoiced when I heard them say</title>
    </titles>
    <verseOrder>v1 c1 v2 c1 v3 c1 v4 c1 v5 c1</verseOrder>
    <authors>
      <author>Author Unknown</author>
    </authors>
  </properties>
  <lyrics>
    <verse name="v1">
      <lines><br/>I rejoiced when I heard them say<br/>'Let us go to the house of God'<br/>and now our feet are standing<br/>in your gates, O Jerusalem!</lines>
    </verse>
    <verse name="v2">
      <lines><br/>Like a temple of unity<br/>is the city, Jerusalem.<br/>It is there all tribes will gather,<br/>all the tribes of the house of God.</lines>
    </verse>
    <verse name="v3">
      <lines><br/>It is faithful to Israel's law,<br/>there to praise the name of God.<br/>All the judgement seats of David<br/>were set down in Jerusalem.</lines>
    </verse>
    <verse name="v4">
      <lines><br/>For the peace of the nations, pray:<br/>for God's peace within your homes.<br/>May God's lasting peace surround us;<br/>may it dwell in Jerusalem.</lines>
    </verse>
    <verse name="v5">
      <lines><br/>For the love of friends and kin<br/>I will bless you with signs of peace.<br/>For the love of God's own people<br/>I will labour and pray for you.</lines>
    </verse>
    <verse name="c1">
      <lines><br/>Shalom, shalom, the peace of God be here.<br/>Shalom, shalom, God's justice be ever near.</lines>
    </verse>
  </lyrics>
</song>
